jscaller/__init__.py
jscaller/_compatiable.py
jscaller/_engine.py
jscaller/engine.py
jscaller/express.py
jscaller/session.py
PyJSCaller-0.2.0.dist-info/LICENSE
PyJSCaller-0.2.0.dist-info/METADATA
PyJSCaller-0.2.0.dist-info/WHEEL
PyJSCaller-0.2.0.dist-info/top_level.txt
PyJSCaller-0.2.0.dist-info/RECORD
