Metadata-Version: 2.1
Name: PyJSCaller
Version: 0.2.0
Summary: Run JavaScript code from Python
Home-page: https://github.com/ZSAIm/PyJSCaller
Author: ZSAIm
Author-email: zzsaim@163.com
License: MIT License
Platform: UNKNOWN
Classifier: Development Status :: 5 - Production/Stable
Classifier: Intended Audience :: Developers
Classifier: License :: OSI Approved :: MIT License
Classifier: Programming Language :: Python
Classifier: Programming Language :: Python :: 2.7
Classifier: Programming Language :: Python :: 3
Classifier: Programming Language :: Python :: 3.7
Classifier: Programming Language :: JavaScript
